src/__init__.py
src/supersodcli.py
src/commands/__init__.py
src/commands/authorize.py
src/commands/loadcsv.py
src/commands/onfleettasks.py
src/commands/polling.py
supersod_cli-0.3.1.dist-info/LICENSE
supersod_cli-0.3.1.dist-info/METADATA
supersod_cli-0.3.1.dist-info/WHEEL
supersod_cli-0.3.1.dist-info/entry_points.txt
supersod_cli-0.3.1.dist-info/top_level.txt
supersod_cli-0.3.1.dist-info/RECORD
