Metadata-Version: 2.1
Name: supersod-cli
Version: 0.3.1
Summary: Super Sod Command Line Interface
Author-email: Hunter Boyd <hboyd@supersod.com>
Project-URL: Homepage, https://github.com/hunterjsb/supersod-cli
Project-URL: Bug Tracker, https://github.com/hunterjsb/supersod-cli/issues
Classifier: Programming Language :: Python :: 3
Classifier: License :: OSI Approved :: MIT License
Classifier: Operating System :: OS Independent
Requires-Python: >=3.7
License-File: LICENSE
Requires-Dist: click
Requires-Dist: requests
Requires-Dist: keyring
Requires-Dist: pyonfleet
